MartysTestModule/Module1.py
MartysTestModule/Module2.py
MartysTestModule/__init__.py
MartysTestModule-0.0.2.dist-info/LICENSE.txt
MartysTestModule-0.0.2.dist-info/METADATA
MartysTestModule-0.0.2.dist-info/WHEEL
MartysTestModule-0.0.2.dist-info/top_level.txt
MartysTestModule-0.0.2.dist-info/RECORD
