Metadata-Version: 2.1
Name: MartysTestModule
Version: 0.0.2
Summary: Test Take 2
Home-page: UNKNOWN
Author: Marty DeWitt
Author-email: martydewitt2015@gmail.com
License: MIT
Platform: UNKNOWN
